snowflakes/__init__.py
snowflakes/_version.py
snowflakes/helpers.py
snowflakes-0.0.1.dist-info/METADATA
snowflakes-0.0.1.dist-info/WHEEL
snowflakes-0.0.1.dist-info/top_level.txt
snowflakes-0.0.1.dist-info/RECORD
